hi_chem/__init__.py
hi_chem/__version__.py
hi_chem/app.py
hi_chem/conformer.py
hi_chem/translate.py
hi_chem/view.py
dev_hi_chem-0.0.1.dist-info/LICENSE
dev_hi_chem-0.0.1.dist-info/METADATA
dev_hi_chem-0.0.1.dist-info/WHEEL
dev_hi_chem-0.0.1.dist-info/entry_points.txt
dev_hi_chem-0.0.1.dist-info/top_level.txt
dev_hi_chem-0.0.1.dist-info/RECORD
