Metadata-Version: 2.1
Name: dev-hi-chem
Version: 0.0.1
Summary: dev-hi-chem - A template Python package for Harms Informatics
Home-page: https://github.com/HarmsInformatics/hi-chem
Author: Nate Harms
Author-email: harmsinformatics@gmail.com
License: MIT
Keywords: package development template
Classifier: Development Status :: 4 - Beta
Classifier: Intended Audience :: Developers
Classifier: Programming Language :: Python :: 3.9
Requires-Python: >=3.9
License-File: LICENSE
Requires-Dist: numpy
Requires-Dist: requests
Requires-Dist: pandas
Requires-Dist: seaborn
Requires-Dist: matplotlib
Requires-Dist: typer
Requires-Dist: rdkit
Requires-Dist: py3dmol
Requires-Dist: jupyter
Requires-Dist: ipython
